README.rst
setup.cfg
setup.py
scripts/__init__.py
tests/__init__.py
tests/test_caching.py
tests/test_dynamic_jobs.py
tests/test_exceptions.py
tests/test_extractor_dec.py
tests/test_job_def_dec.py
tests/test_job_injection.py
tests/test_job_order.py
tests/test_logging.py
tests/test_parent_data_param.py
tests/test_transformer_dec.py
tests/test_tree.py
treetl/__init__.py
treetl.egg-info/PKG-INFO
treetl.egg-info/SOURCES.txt
treetl.egg-info/dependency_links.txt
treetl.egg-info/not-zip-safe
treetl.egg-info/top_level.txt
treetl/job/__init__.py
treetl/job/_job.py
treetl/job/_jobrunner.py
treetl/tools/__init__.py
treetl/tools/joblogging.py
treetl/tools/polytree.py
treetl/tools/testing.py